{
    "simalateEmptySchedule": "false",
    "simalateEmptyResults": "true",
    "ranking": [
        {
            "title": "Grupa A",
            "teams": [
                {
                    "team": "The Teachers",
                    "points": "0"
                },
                {
                    "team": "Betel Ipotești",
                    "points": "0"
                },
                {
                    "team": "No Name",
                    "points": "0"
                },
                {
                    "team": "ODEM",
                    "points": "0"
                }
            ]
        },
        {
            "title": "Grupa B",
            "teams": [
                {
                    "team": "Saint Elijah",
                    "points": "0"
                },
                {
                    "team": "Spartans",
                    "points": "0"
                },
                {
                    "team": "Eternal Flames",
                    "points": "0"
                },
                {
                    "team": "Karasuno",
                    "points": "0"
                }
            ]
        },
        {
            "title": "Grupa C",
            "teams": [
                {
                    "team": "Spike for Hope",
                    "points": "0"
                },
                {
                    "team": "Bullet Team",
                    "points": "0"
                },
                {
                    "team": "Living Stone",
                    "points": "0"
                },
                {
                    "team": "Samson's Biceps",
                    "points": "0"
                }
            ]
        },
        {
            "title": "Grupa D",
            "teams": [
                {
                    "team": "Flashback",
                    "points": "0"
                },
                {
                    "team": "Holy hits different",
                    "points": "0"
                },
                {
                    "team": "Bethel Warriors",
                    "points": "0"
                },
                {
                    "team": "Wave Crushers",
                    "points": "0"
                }
            ]
        }
    ],
    "grupStage": [
        {
            "hour": "16:00",
            "day": "vineri",
            "team1": "Echipa 1 grupa A",
            "logoTeam1": "",
            "team2": "Echipa 2 grupa A",
            "logoTeam2": "",
            "generalScore": "-",
            "set1": "-",
            "set2": "-",
            "set3": "-"
        }
    ],
    "quarter": [
        {
            "hour": "08:00",
            "day": "sâmbătă",
            "team1": "Echipă 1 sfert 1",
            "logoTeam1": "",
            "team2": "Echipă 2 sfert 1",
            "logoTeam2": "",
            "generalScore": "-",
            "set1": "-",
            "set2": "-",
            "set3": "-"
        },
        {
            "hour": "09:00",
            "day": "sâmbătă",
            "team1": "Echipă 3 sfert 2",
            "logoTeam1": "",
            "team2": "Echipă 4 sfert 2",
            "logoTeam2": "",
            "generalScore": "-",
            "set1": "-",
            "set2": "-",
            "set3": "-"
        },
        {
            "hour": "09:00",
            "day": "sâmbătă",
            "team1": "Echipă 5 sfert 3",
            "logoTeam1": "",
            "team2": "Echipă 6 sfert 3 ",
            "logoTeam2": "",
            "generalScore": "-",
            "set1": "-",
            "set2": "-",
            "set3": "-"
        },
        {
            "hour": "09:00",
            "day": "sâmbătă",
            "team1": "Echipă 7 sfert 4",
            "logoTeam1": "",
            "team2": "Echipă 8 sfert 4",
            "logoTeam2": "",
            "generalScore": "-",
            "set1": "-",
            "set2": "-",
            "set3": "-"
        }
    ],
    "semi": [
        {
            "hour": "10:00",
            "day": "sâmbătă",
            "team1": "Echipă 1 semifinală 1",
            "logoTeam1": "",
            "team2": "Echipa 2 semifinală 1",
            "logoTeam2": "",
            "generalScore": "-",
            "set1": "-",
            "set2": "-",
            "set3": "-"
        },
        {
            "hour": "11:00",
            "day": "sâmbătă",
            "team1": "Echipă 3 semifinală 2",
            "logoTeam1": "",
            "team2": "Echipă 4 semifinală 2",
            "logoTeam2": "",
            "generalScore": "-",
            "set1": "-",
            "set2": "-",
            "set3": "-"
        }
    ],
    "lowerFinal": {
        "hour": "18:00",
        "day": "sâmbătă",
        "team1": "Echipă 1 finala mică",
        "logoTeam1": "",
        "team2": "Echipă 2 finala mică",
        "logoTeam2": "",
        "generalScore": "-",
        "set1": "-",
        "set2": "-",
        "set3": "-"
    },
    "greatFinal": {
        "hour": "19:00",
        "day": "sâmbătă",
        "team1": "Echipă 1 finală",
        "logoTeam1": "",
        "team2": "Echipă 2 finală",
        "logoTeam2": "",
        "generalScore": "-",
        "set1": "-",
        "set2": "-",
        "set3": "-"
    }
}